python_jamf/VERSION
python_jamf/__init__.py
python_jamf/api.py
python_jamf/config.py
python_jamf/convert.py
python_jamf/exceptions.py
python_jamf/package.py
python_jamf/records.py
python_jamf/server.py
python_jamf/setconfig.py
python_jamf/version.py
tests/__init__.py
tests/api_test_old.py
tests/config_test.py
tests/convert_json_xml_test.py
tests/test_records.py
python_jamf-0.9.9.dist-info/LICENSE
python_jamf-0.9.9.dist-info/METADATA
python_jamf-0.9.9.dist-info/WHEEL
python_jamf-0.9.9.dist-info/entry_points.txt
python_jamf-0.9.9.dist-info/top_level.txt
python_jamf-0.9.9.dist-info/RECORD
