Metadata-Version: 2.1
Name: python-jamf
Version: 0.9.9
Summary: Python wrapper for Jamf Pro API
Home-page: https://github.com/univ-of-utah-marriott-library-apple/python-jamf
Author: The University of Utah
Author-email: mlib-its-mac@lists.utah.edu
License: MIT
Classifier: Programming Language :: Python :: 3
Classifier: License :: OSI Approved :: MIT License
Classifier: Operating System :: OS Independent
Classifier: Development Status :: 4 - Beta
Requires-Python: >=3.6
License-File: LICENSE
Requires-Dist: requests >=2.24.0
Requires-Dist: keyring >=23.0.0
Requires-Dist: jps-api-wrapper >=1.0.6
